autosuggest/__init__.py
autosuggest-1.1.1.dist-info/LICENSE
autosuggest-1.1.1.dist-info/METADATA
autosuggest-1.1.1.dist-info/WHEEL
autosuggest-1.1.1.dist-info/top_level.txt
autosuggest-1.1.1.dist-info/RECORD
