Metadata-Version: 2.1
Name: autosuggest
Version: 1.1.1
Summary: A cross-platform auto-suggest input package with enhanced features
Home-page: https://github.com/ishanoshada/autosuggest
Author: Ishan OShada
Author-email: ic31908@gmail.com
Classifier: Programming Language :: Python :: 3
Classifier: Operating System :: OS Independent
Requires-Python: >=3.6
License-File: LICENSE
